stylizers/__init__.py
stylizers/textStyle.py
stylizers-0.0.1.dist-info/METADATA
stylizers-0.0.1.dist-info/WHEEL
stylizers-0.0.1.dist-info/top_level.txt
stylizers-0.0.1.dist-info/RECORD
