Metadata-Version: 2.1
Name: stylizers
Version: 0.0.1
Summary: A Beautiful Library which will modify your Beautiful Name into an Extraordinary Styled Name.
Home-page: https://github.com/DivyanshuSingh96/stylizers
Author: Divyanshu Singh
Author-email: divyanshu.singh144400@gmail.com
License: MIT
Platform: UNKNOWN
Classifier: License :: OSI Approved :: MIT License
Classifier: Programming Language :: Python :: 3
Classifier: Operating System :: OS Independent
Requires-Python: >=3.0
